hydropandas/__init__.py
hydropandas/obs_collection.py
hydropandas/observation.py
hydropandas/rcparams.py
hydropandas/serialization.py
hydropandas/util.py
hydropandas/version.py
hydropandas/data/fews_parameterid.py
hydropandas/data/knmi_meteostation.json
hydropandas/data/knmi_neerslagstation.json
hydropandas/data/matroos_params.json
hydropandas/data/update_knmi_stations.py
hydropandas/data/update_matroos.py
hydropandas/extensions/__init__.py
hydropandas/extensions/accessor.py
hydropandas/extensions/geo.py
hydropandas/extensions/gwobs.py
hydropandas/extensions/plots.py
hydropandas/extensions/stats.py
hydropandas/io/__init__.py
hydropandas/io/bro.py
hydropandas/io/bronhouderportaal_bro.py
hydropandas/io/dino.py
hydropandas/io/fews.py
hydropandas/io/knmi.py
hydropandas/io/lizard.py
hydropandas/io/matroos.py
hydropandas/io/menyanthes.py
hydropandas/io/modflow.py
hydropandas/io/pastas.py
hydropandas/io/solinst.py
hydropandas/io/water_connect.py
hydropandas/io/waterinfo.py
hydropandas/io/wiski.py
hydropandas/io/wow.py
hydropandas/static/js_collapse.html
hydropandas/static/style.css
hydropandas-0.18.0.dist-info/licenses/LICENSE
hydropandas-0.18.0.dist-info/METADATA
hydropandas-0.18.0.dist-info/WHEEL
hydropandas-0.18.0.dist-info/top_level.txt
hydropandas-0.18.0.dist-info/RECORD
