Metadata-Version: 2.4
Name: hydropandas
Version: 0.18.0
Summary: Module by Artesia for loading observation data into custom DataFrames.
Author-email: Onno Ebbens <o.ebbens@artesia-water.nl>
Maintainer-email: "O.N. Ebbens" <o.ebbens@artesia-water.nl>, "R. Calje" <r.calje@artesia-water.nl>, "D.A. Brakenhoff" <d.brakenhoff@artesia-water.nl>, "M.A. Vonk" <m.vonk@artesia-water.nl>
License: The MIT License (MIT)
Project-URL: homepage, https://www.artesia-water.nl
Project-URL: repository, https://github.com/artesiawater/hydropandas
Project-URL: documentation, https://hydropandas.readthedocs.io/en/stable/
Classifier: Development Status :: 4 - Beta
Classifier: Intended Audience :: Science/Research
Classifier: Intended Audience :: Other Audience
Classifier: License :: OSI Approved :: MIT License
Classifier: Programming Language :: Python :: 3 :: Only
Classifier: Programming Language :: Python :: 3.10
Classifier: Programming Language :: Python :: 3.11
Classifier: Programming Language :: Python :: 3.12
Classifier: Programming Language :: Python :: 3.13
Classifier: Operating System :: OS Independent
Classifier: Topic :: Scientific/Engineering :: Hydrology
Requires-Python: >=3.10
License-File: LICENSE
Requires-Dist: scipy
Requires-Dist: pandas
Requires-Dist: matplotlib
Requires-Dist: tqdm
Requires-Dist: requests
Requires-Dist: colorama
Requires-Dist: geopandas
Requires-Dist: pyproj
Requires-Dist: contextily
Requires-Dist: bokeh
Requires-Dist: branca
Requires-Dist: folium
Requires-Dist: rws-ddlpy
Requires-Dist: pastastore>=1.10.2
Provides-Extra: full
Requires-Dist: openpyxl; extra == "full"
Requires-Dist: pastastore; extra == "full"
Requires-Dist: flopy; extra == "full"
Requires-Dist: xarray; extra == "full"
Requires-Dist: netCDF4; extra == "full"
Requires-Dist: lxml; extra == "full"
Requires-Dist: pyarrow; extra == "full"
Requires-Dist: brodata>=0.1.4; extra == "full"
Provides-Extra: rtd
Requires-Dist: hydropandas[full]; extra == "rtd"
Requires-Dist: imod; extra == "rtd"
Requires-Dist: requests; extra == "rtd"
Requires-Dist: nbconvert; extra == "rtd"
Requires-Dist: ipykernel; extra == "rtd"
Requires-Dist: docutils<0.18; extra == "rtd"
Requires-Dist: sphinx_rtd_theme; extra == "rtd"
Requires-Dist: Ipython; extra == "rtd"
Requires-Dist: nbsphinx; extra == "rtd"
Requires-Dist: nbsphinx_link; extra == "rtd"
Provides-Extra: ruffing
Requires-Dist: ruff; extra == "ruffing"
Provides-Extra: pytesting
Requires-Dist: hydropandas[full,rtd]; extra == "pytesting"
Requires-Dist: pytest>=7; extra == "pytesting"
Requires-Dist: pytest-cov; extra == "pytesting"
Requires-Dist: pytest-sugar; extra == "pytesting"
Provides-Extra: coveraging
Requires-Dist: coverage; extra == "coveraging"
Provides-Extra: dev
Requires-Dist: hydropandas[pytesting,ruffing]; extra == "dev"
Requires-Dist: tox; extra == "dev"
Dynamic: license-file
